Workbook

Sheet MASTER_PRODUCTS
A1: Product Code | B1: Product Name | C1: UOM
A2: FG001 | B2: AVION STRAWS | C2: CTNS
A3: FG002 | B3: WAVEX STRAWS | C3: CTNS
A4: FG003 | B4: CHINESE JUICE STRAWS | C4: KGS
A5: FG004 | B5: MUZURI STICKS 105MM | C5: KGS
A6: FG005 | B6: MUZURI STICKS 69MM | C6: KGS
A7: FG006 | B7: MUZURI STICKS 175MM | C7: KGS
A8: FG007 | B8: CANDY STICKS 95MM | C8: KGS
A9: FG008 | B9: MUKONO STICKS 175MM | C9: KGS
A10: FG009 | B10: MUKONO STICKS 105MM | C10: KGS
A11: FG010 | B11: NEW STICK CUSTOMER 1 | C11: KGS
A12: FG011 | B12: NEW STICK CUSTOMER 2 | C12: KGS
... A38: FG037 | B38: NON GOLDEN 25 MTR FOIL | C38: CTNS

Sheet MASTER_RAW_MATERIALS
A1: RM Code | B1: Raw Material | C1: UOM | D1: Opening Stock | E1: RM Price | F1: Min Stock
A2: RM001 | B2: MASTER BATCH PINK | C2: KG | D2: 1500 | E2: 1000 | F2: 1000
A3: RM002 | B3: MASTER BATCH WHITE | C3: KG | D3: 1500 | E3: 200 | F3: 1000
A4: RM003 | B4: AVION INNER KAVERA | C4: KG | D4: 1500 | E4: 200 | F4: 1000
A5: RM004 | B5: WAVEX INNER KAVERA | C5: KG | D5: 1500 | E5: 200 | F5: 1000
A6: RM005 | B6: AVION OUTER KAVERA | C6: KG | D6: 1500 | E6: 200 | F6: 1000
A7: RM006 | B7: WAVEX OUTER KAVERA | C7: KG | D7: 1500 | E7: 200 | F7: 1000
A8: RM007 | B8: WRAPPING PAPPER | C8: KG | D8: 1500 | E8: 200 | F8: 1000
A9: RM008 | B9: STICK KAVERA | C9: KG | D9: 1500 | E9: 200 | F9: 1000
A10: RM009 | B10: CHINESE KAVERA | C10: KG | D10: 1500 | E10: 200 | F10: 1000
A11: RM010 | B11: 14 MICRON FOIL 45 CM | C11: KG | D11: 1500 | E11: 200 | F11: 1000
A12: RM011 | B12: YOLO INNER KAVERA | C12: KG | D12: 1500 | E12: 200 | F12: 1000
A13: RM012 | B13: GOLDEN PVC OUTER(1 X25) | C13: PCS | D13: 1500 | E13: 200 | F13: 1000
... A52: RM051 | B52: FILLER | C52: KG | D52: 1500 | E52: 200 | F52: 1000

Sheet BOM
A1: Finished Product | B1: Raw Material | C1: Standard Qty Per Unit
A2: CHINESE JUICE STRAWS | B2: PP | C2: 1.015
A3: CHINESE JUICE STRAWS | B3: CHINESE KAVERA | C3: 0.005
A4: MUZURI STICKS 105MM | B4: PP | C4: 1.015
A5: MUZURI STICKS 105MM | B5: MASTER BATCH WHITE | C5: 0.004
A6: MUZURI STICKS 105MM | B6: STICK KAVERA | C6: 0.005
A7: MUZURI STICKS 105MM | B7: FILLER | C7: 0.3
A8: MUZURI STICKS 69MM | B8: PP | C8: 1.015
A9: MUZURI STICKS 69MM | B9: MASTER BATCH WHITE | C9: 0.004
A10: MUZURI STICKS 69MM | B10: STICK KAVERA | C10: 0.005
A11: MUZURI STICKS 69MM | B11: FILLER | C11: 0.3
A12: MUZURI STICKS 175MM | B12: PP | C12: 1.015
A13: MUZURI STICKS 175MM | B13: MASTER BATCH WHITE | C13: 0.004
... A85: AVION 5 MTR FOIL | B85: CYRSTAL WRAP OUTER -5m(1 X25) | C85: 1
A86: GOLDEN 150 MTR X 30CM FOIL | B86: 14 MICRON FOIL 30 CM | C86: =10.2/6 -> 1.7
A87: GOLDEN 150 MTR X 30CM FOIL | B87: PAPER CORE 37 MM | C87: 1
A88: GOLDEN 150 MTR X 30CM FOIL | B88: LAMINATER GOLDEN FOIL INNER 30cm (1 X 30 ) | C88: 1
A89: GOLDEN 150 MTR X 30CM FOIL | B89: BLADES 30cm ( Each bundles : 0.grm ) | C89: 1
A90: GOLDEN 30 MTR FOIL | B90: 14 MICRON FOIL 45 CM | C90: 3.107
A91: GOLDEN 30 MTR FOIL | B91: PAPER CORE 37 MM | C91: 6
A92: GOLDEN 30 MTR FOIL | B92: GOLDEN FOIL INNER 45CM( 1 X 25 ) | C92: 6
A93: GOLDEN 30 MTR FOIL | B93: GOLDEN FOIL OUTER(1 X25) | C93: 1
A94: GOLDEN 30 MTR FOIL | B94: BLADES 45cm ( Each bundles : 0.84 grm ) | C94: 6
A95: GOLDEN 50 MTR FOIL | B95: 14 MICRON FOIL 45 CM | C95: 5.12
A96: GOLDEN 50 MTR FOIL | B96: PAPER CORE 37 MM | C96: 6
A97: GOLDEN 50 MTR FOIL | B97: GOLDEN FOIL INNER 45CM( 1 X 25 ) | C97: 6
A98: GOLDEN 50 MTR FOIL | B98: GOLDEN FOIL OUTER(1 X25) | C98: 1
... A152: GOLDEN 25 MTR FOIL | B152: BLADES 45cm ( Each bundles : 0.84 grm ) | C152: 6

Sheet PURCHASES
A1: Date | B1: Invoice No | C1: Supplier | D1: Raw Material | E1: Qty | F1: Rate | G1: Purchase Value
A2: 46153 | C2: SOMUCHEM | D2: PP | E2: 5000 | G2: =IF(E2="","",E2*F2) -> 0
G3: =IF(E3="","",E3*F3)
G4: =IF(E4="","",E4*F4)
G5: =IF(E5="","",E5*F5)
G6: =IF(E6="","",E6*F6)
G7: =IF(E7="","",E7*F7)
G8: =IF(E8="","",E8*F8)
G9: =IF(E9="","",E9*F9)
G10: =IF(E10="","",E10*F10)
G11: =IF(E11="","",E11*F11)
G12: =IF(E12="","",E12*F12)
G13: =IF(E13="","",E13*F13)
G14: =IF(E14="","",E14*F14)
... G999: =IF(E999="","",E999*F999)

Sheet PRODUCTION_REPORT
A1: Date | B1: Product | C1: Qty Produced | D1: RM1 | E1: Qty1 | F1: RM2 | G1: Qty2 | H1: RM3 | I1: Qty3 | J1: RM4 | K1: Qty4 | L1: RM5 | M1: Qty5 | N1: RM6 | O1: Qty6
A2: 46152 | B2: YOLO STRAW | C2: 300 | D2: PP | E2: 310
A3: 46152 | B3: AVION SMALL SILVER PLATE 8342 | C3: 50 | D3: 37 MICRON FOIL 37.5 CM | E3: 200

Sheet SALES
A1: Date | B1: Invoice No | C1: Customer | D1: Product | E1: Qty Sold | F1: Rate | G1: Sales Value
A2: 46153 | C2: JALSHI OFFICE | D2: YOLO STRAW | E2: 100 | G2: =IF(E2="","",E2*F2) -> 0
A3: 46153 | C3: JALSHI OFFICE | D3: AVION SMALL SILVER PLATE 8342 | E3: 35 | G3: =IF(E3="","",E3*F3) -> 0
G4: =IF(E4="","",E4*F4)
G5: =IF(E5="","",E5*F5)
G6: =IF(E6="","",E6*F6)
G7: =IF(E7="","",E7*F7)
G8: =IF(E8="","",E8*F8)
G9: =IF(E9="","",E9*F9)
G10: =IF(E10="","",E10*F10)
G11: =IF(E11="","",E11*F11)
G12: =IF(E12="","",E12*F12)
G13: =IF(E13="","",E13*F13)
G14: =IF(E14="","",E14*F14)
G15: =IF(E15="","",E15*F15)
... G999: =IF(E999="","",E999*F999)

Sheet STOCK_LEDGER
A1: Raw Material | B1: Opening Stock | C1: Purchased Qty | D1: Actual Consumption | E1: Closing Stock | F1: RM Price | G1: Stock Value
A2: =IF(MASTER_RAW_MATERIALS!B2="","",MASTER_RAW_MATERIALS!B2) -> MASTER BATCH PINK | B2: =IF(A2="","",MASTER_RAW_MATERIALS!D2) -> 1500 | C2: =IF(A2="","",SUMIFS(PURCHASES!E:E,PURCHASES!D:D,A2)) -> 0 | D2: =IF(A2="","",SUMIFS(PRODUCTION_REPORT!E:E,PRODUCTION_REPORT!D:D,A2)+SUMIFS(PRODUCTION_REPORT!G:G,PRODUCTION_REPORT!F:F,A2)+SUMIFS(PRODUCTION_REPORT!I:I,PRODUCTION_REPORT!H:H,A2)+SUMIFS(PRODUCTION_REPORT!K:K,PRODUCTION_REPORT!J:J,A2)+SUMIFS(PRODUCTION_REPORT!M:M,PRODUCTION_REPORT!L:L,A2)+SUMIFS(PRODUCTION_REPORT!O:O,PRODUCTION_REPORT!N:N,A2)) -> 0 | E2: =IF(A2="","",B2+C2-D2) -> 1500 | F2: =IF(A3="","",_xlfn.XLOOKUP(A2,MASTER_RAW_MATERIALS!B:B,MASTER_RAW_MATERIALS!E:E,0)) -> 1000 | G2: =IF(A2="","",E2*F2) -> 1500000
A3: =IF(MASTER_RAW_MATERIALS!B3="","",MASTER_RAW_MATERIALS!B3) -> MASTER BATCH WHITE | B3: =IF(A3="","",MASTER_RAW_MATERIALS!D3) -> 1500 | C3: =IF(A3="","",SUMIFS(PURCHASES!E:E,PURCHASES!D:D,A3)) -> 0 | D3: =IF(A3="","",SUMIFS(PRODUCTION_REPORT!E:E,PRODUCTION_REPORT!D:D,A3)+SUMIFS(PRODUCTION_REPORT!G:G,PRODUCTION_REPORT!F:F,A3)+SUMIFS(PRODUCTION_REPORT!I:I,PRODUCTION_REPORT!H:H,A3)+SUMIFS(PRODUCTION_REPORT!K:K,PRODUCTION_REPORT!J:J,A3)+SUMIFS(PRODUCTION_REPORT!M:M,PRODUCTION_REPORT!L:L,A3)+SUMIFS(PRODUCTION_REPORT!O:O,PRODUCTION_REPORT!N:N,A3)) -> 0 | E3: =IF(A3="","",B3+C3-D3) -> 1500 | F3: =IF(A3="","",_xlfn.XLOOKUP(A3,MASTER_RAW_MATERIALS!B:B,MASTER_RAW_MATERIALS!E:E,0)) -> 200 | G3: =IF(A3="","",E3*F3) -> 300000 | H3: =MASTER_RAW_MATERIALS!E2 -> 1000
A4: =IF(MASTER_RAW_MATERIALS!B4="","",MASTER_RAW_MATERIALS!B4) -> AVION INNER KAVERA | B4: =IF(A4="","",MASTER_RAW_MATERIALS!D4) -> 1500 | C4: =IF(A4="","",SUMIFS(PURCHASES!E:E,PURCHASES!D:D,A4)) -> 0 | D4: =IF(A4="","",SUMIFS(PRODUCTION_REPORT!E:E,PRODUCTION_REPORT!D:D,A4)+SUMIFS(PRODUCTION_REPORT!G:G,PRODUCTION_REPORT!F:F,A4)+SUMIFS(PRODUCTION_REPORT!I:I,PRODUCTION_REPORT!H:H,A4)+SUMIFS(PRODUCTION_REPORT!K:K,PRODUCTION_REPORT!J:J,A4)+SUMIFS(PRODUCTION_REPORT!M:M,PRODUCTION_REPORT!L:L,A4)+SUMIFS(PRODUCTION_REPORT!O:O,PRODUCTION_REPORT!N:N,A4)) -> 0 | E4: =IF(A4="","",B4+C4-D4) -> 1500 | F4: =IF(A4="","",_xlfn.XLOOKUP(A4,MASTER_RAW_MATERIALS!B:B,MASTER_RAW_MATERIALS!E:E,0)) -> 200 | G4: =IF(A4="","",E4*F4) -> 300000 | H4: =ISTEXT(B2) -> FALSE
A5: =IF(MASTER_RAW_MATERIALS!B5="","",MASTER_RAW_MATERIALS!B5) -> WAVEX INNER KAVERA | B5: =IF(A5="","",MASTER_RAW_MATERIALS!D5) -> 1500 | C5: =IF(A5="","",SUMIFS(PURCHASES!E:E,PURCHASES!D:D,A5)) -> 0 | D5: =IF(A5="","",SUMIFS(PRODUCTION_REPORT!E:E,PRODUCTION_REPORT!D:D,A5)+SUMIFS(PRODUCTION_REPORT!G:G,PRODUCTION_REPORT!F:F,A5)+SUMIFS(PRODUCTION_REPORT!I:I,PRODUCTION_REPORT!H:H,A5)+SUMIFS(PRODUCTION_REPORT!K:K,PRODUCTION_REPORT!J:J,A5)+SUMIFS(PRODUCTION_REPORT!M:M,PRODUCTION_REPORT!L:L,A5)+SUMIFS(PRODUCTION_REPORT!O:O,PRODUCTION_REPORT!N:N,A5)) -> 0 | E5: =IF(A5="","",B5+C5-D5) -> 1500 | F5: =IF(A5="","",_xlfn.XLOOKUP(A5,MASTER_RAW_MATERIALS!B:B,MASTER_RAW_MATERIALS!E:E,0)) -> 200 | G5: =IF(A5="","",E5*F5) -> 300000
A6: =IF(MASTER_RAW_MATERIALS!B6="","",MASTER_RAW_MATERIALS!B6) -> AVION OUTER KAVERA | B6: =IF(A6="","",MASTER_RAW_MATERIALS!D6) -> 1500 | C6: =IF(A6="","",SUMIFS(PURCHASES!E:E,PURCHASES!D:D,A6)) -> 0 | D6: =IF(A6="","",SUMIFS(PRODUCTION_REPORT!E:E,PRODUCTION_REPORT!D:D,A6)+SUMIFS(PRODUCTION_REPORT!G:G,PRODUCTION_REPORT!F:F,A6)+SUMIFS(PRODUCTION_REPORT!I:I,PRODUCTION_REPORT!H:H,A6)+SUMIFS(PRODUCTION_REPORT!K:K,PRODUCTION_REPORT!J:J,A6)+SUMIFS(PRODUCTION_REPORT!M:M,PRODUCTION_REPORT!L:L,A6)+SUMIFS(PRODUCTION_REPORT!O:O,PRODUCTION_REPORT!N:N,A6)) -> 0 | E6: =IF(A6="","",B6+C6-D6) -> 1500 | F6: =IF(A6="","",_xlfn.XLOOKUP(A6,MASTER_RAW_MATERIALS!B:B,MASTER_RAW_MATERIALS!E:E,0)) -> 200 | G6: =IF(A6="","",E6*F6) -> 300000
A7: =IF(MASTER_RAW_MATERIALS!B7="","",MASTER_RAW_MATERIALS!B7) -> WAVEX OUTER KAVERA | B7: =IF(A7="","",MASTER_RAW_MATERIALS!D7) -> 1500 | C7: =IF(A7="","",SUMIFS(PURCHASES!E:E,PURCHASES!D:D,A7)) -> 0 | D7: =IF(A7="","",SUMIFS(PRODUCTION_REPORT!E:E,PRODUCTION_REPORT!D:D,A7)+SUMIFS(PRODUCTION_REPORT!G:G,PRODUCTION_REPORT!F:F,A7)+SUMIFS(PRODUCTION_REPORT!I:I,PRODUCTION_REPORT!H:H,A7)+SUMIFS(PRODUCTION_REPORT!K:K,PRODUCTION_REPORT!J:J,A7)+SUMIFS(PRODUCTION_REPORT!M:M,PRODUCTION_REPORT!L:L,A7)+SUMIFS(PRODUCTION_REPORT!O:O,PRODUCTION_REPORT!N:N,A7)) -> 0 | E7: =IF(A7="","",B7+C7-D7) -> 1500 | F7: =IF(A7="","",_xlfn.XLOOKUP(A7,MASTER_RAW_MATERIALS!B:B,MASTER_RAW_MATERIALS!E:E,0)) -> 200 | G7: =IF(A7="","",E7*F7) -> 300000
A8: =IF(MASTER_RAW_MATERIALS!B8="","",MASTER_RAW_MATERIALS!B8) -> WRAPPING PAPPER | B8: =IF(A8="","",MASTER_RAW_MATERIALS!D8) -> 1500 | C8: =IF(A8="","",SUMIFS(PURCHASES!E:E,PURCHASES!D:D,A8)) -> 0 | D8: =IF(A8="","",SUMIFS(PRODUCTION_REPORT!E:E,PRODUCTION_REPORT!D:D,A8)+SUMIFS(PRODUCTION_REPORT!G:G,PRODUCTION_REPORT!F:F,A8)+SUMIFS(PRODUCTION_REPORT!I:I,PRODUCTION_REPORT!H:H,A8)+SUMIFS(PRODUCTION_REPORT!K:K,PRODUCTION_REPORT!J:J,A8)+SUMIFS(PRODUCTION_REPORT!M:M,PRODUCTION_REPORT!L:L,A8)+SUMIFS(PRODUCTION_REPORT!O:O,PRODUCTION_REPORT!N:N,A8)) -> 0 | E8: =IF(A8="","",B8+C8-D8) -> 1500 | F8: =IF(A8="","",_xlfn.XLOOKUP(A8,MASTER_RAW_MATERIALS!B:B,MASTER_RAW_MATERIALS!E:E,0)) -> 200 | G8: =IF(A8="","",E8*F8) -> 300000
A9: =IF(MASTER_RAW_MATERIALS!B9="","",MASTER_RAW_MATERIALS!B9) -> STICK KAVERA | B9: =IF(A9="","",MASTER_RAW_MATERIALS!D9) -> 1500 | C9: =IF(A9="","",SUMIFS(PURCHASES!E:E,PURCHASES!D:D,A9)) -> 0 | D9: =IF(A9="","",SUMIFS(PRODUCTION_REPORT!E:E,PRODUCTION_REPORT!D:D,A9)+SUMIFS(PRODUCTION_REPORT!G:G,PRODUCTION_REPORT!F:F,A9)+SUMIFS(PRODUCTION_REPORT!I:I,PRODUCTION_REPORT!H:H,A9)+SUMIFS(PRODUCTION_REPORT!K:K,PRODUCTION_REPORT!J:J,A9)+SUMIFS(PRODUCTION_REPORT!M:M,PRODUCTION_REPORT!L:L,A9)+SUMIFS(PRODUCTION_REPORT!O:O,PRODUCTION_REPORT!N:N,A9)) -> 0 | E9: =IF(A9="","",B9+C9-D9) -> 1500 | F9: =IF(A9="","",_xlfn.XLOOKUP(A9,MASTER_RAW_MATERIALS!B:B,MASTER_RAW_MATERIALS!E:E,0)) -> 200 | G9: =IF(A9="","",E9*F9) -> 300000
A10: =IF(MASTER_RAW_MATERIALS!B10="","",MASTER_RAW_MATERIALS!B10) -> CHINESE KAVERA | B10: =IF(A10="","",MASTER_RAW_MATERIALS!D10) -> 1500 | C10: =IF(A10="","",SUMIFS(PURCHASES!E:E,PURCHASES!D:D,A10)) -> 0 | D10: =IF(A10="","",SUMIFS(PRODUCTION_REPORT!E:E,PRODUCTION_REPORT!D:D,A10)+SUMIFS(PRODUCTION_REPORT!G:G,PRODUCTION_REPORT!F:F,A10)+SUMIFS(PRODUCTION_REPORT!I:I,PRODUCTION_REPORT!H:H,A10)+SUMIFS(PRODUCTION_REPORT!K:K,PRODUCTION_REPORT!J:J,A10)+SUMIFS(PRODUCTION_REPORT!M:M,PRODUCTION_REPORT!L:L,A10)+SUMIFS(PRODUCTION_REPORT!O:O,PRODUCTION_REPORT!N:N,A10)) -> 0 | E10: =IF(A10="","",B10+C10-D10) -> 1500 | F10: =IF(A10="","",_xlfn.XLOOKUP(A10,MASTER_RAW_MATERIALS!B:B,MASTER_RAW_MATERIALS!E:E,0)) -> 200 | G10: =IF(A10="","",E10*F10) -> 300000
A11: =IF(MASTER_RAW_MATERIALS!B11="","",MASTER_RAW_MATERIALS!B11) -> 14 MICRON FOIL 45 CM | B11: =IF(A11="","",MASTER_RAW_MATERIALS!D11) -> 1500 | C11: =IF(A11="","",SUMIFS(PURCHASES!E:E,PURCHASES!D:D,A11)) -> 0 | D11: =IF(A11="","",SUMIFS(PRODUCTION_REPORT!E:E,PRODUCTION_REPORT!D:D,A11)+SUMIFS(PRODUCTION_REPORT!G:G,PRODUCTION_REPORT!F:F,A11)+SUMIFS(PRODUCTION_REPORT!I:I,PRODUCTION_REPORT!H:H,A11)+SUMIFS(PRODUCTION_REPORT!K:K,PRODUCTION_REPORT!J:J,A11)+SUMIFS(PRODUCTION_REPORT!M:M,PRODUCTION_REPORT!L:L,A11)+SUMIFS(PRODUCTION_REPORT!O:O,PRODUCTION_REPORT!N:N,A11)) -> 0 | E11: =IF(A11="","",B11+C11-D11) -> 1500 | F11: =IF(A11="","",_xlfn.XLOOKUP(A11,MASTER_RAW_MATERIALS!B:B,MASTER_RAW_MATERIALS!E:E,0)) -> 200 | G11: =IF(A11="","",E11*F11) -> 300000
A12: =IF(MASTER_RAW_MATERIALS!B12="","",MASTER_RAW_MATERIALS!B12) -> YOLO INNER KAVERA | B12: =IF(A12="","",MASTER_RAW_MATERIALS!D12) -> 1500 | C12: =IF(A12="","",SUMIFS(PURCHASES!E:E,PURCHASES!D:D,A12)) -> 0 | D12: =IF(A12="","",SUMIFS(PRODUCTION_REPORT!E:E,PRODUCTION_REPORT!D:D,A12)+SUMIFS(PRODUCTION_REPORT!G:G,PRODUCTION_REPORT!F:F,A12)+SUMIFS(PRODUCTION_REPORT!I:I,PRODUCTION_REPORT!H:H,A12)+SUMIFS(PRODUCTION_REPORT!K:K,PRODUCTION_REPORT!J:J,A12)+SUMIFS(PRODUCTION_REPORT!M:M,PRODUCTION_REPORT!L:L,A12)+SUMIFS(PRODUCTION_REPORT!O:O,PRODUCTION_REPORT!N:N,A12)) -> 0 | E12: =IF(A12="","",B12+C12-D12) -> 1500 | F12: =IF(A12="","",_xlfn.XLOOKUP(A12,MASTER_RAW_MATERIALS!B:B,MASTER_RAW_MATERIALS!E:E,0)) -> 200 | G12: =IF(A12="","",E12*F12) -> 300000
A13: =IF(MASTER_RAW_MATERIALS!B13="","",MASTER_RAW_MATERIALS!B13) -> GOLDEN PVC OUTER(1 X25) | B13: =IF(A13="","",MASTER_RAW_MATERIALS!D13) -> 1500 | C13: =IF(A13="","",SUMIFS(PURCHASES!E:E,PURCHASES!D:D,A13)) -> 0 | D13: =IF(A13="","",SUMIFS(PRODUCTION_REPORT!E:E,PRODUCTION_REPORT!D:D,A13)+SUMIFS(PRODUCTION_REPORT!G:G,PRODUCTION_REPORT!F:F,A13)+SUMIFS(PRODUCTION_REPORT!I:I,PRODUCTION_REPORT!H:H,A13)+SUMIFS(PRODUCTION_REPORT!K:K,PRODUCTION_REPORT!J:J,A13)+SUMIFS(PRODUCTION_REPORT!M:M,PRODUCTION_REPORT!L:L,A13)+SUMIFS(PRODUCTION_REPORT!O:O,PRODUCTION_REPORT!N:N,A13)) -> 0 | E13: =IF(A13="","",B13+C13-D13) -> 1500 | F13: =IF(A13="","",_xlfn.XLOOKUP(A13,MASTER_RAW_MATERIALS!B:B,MASTER_RAW_MATERIALS!E:E,0)) -> 200 | G13: =IF(A13="","",E13*F13) -> 300000
A14: =IF(MASTER_RAW_MATERIALS!B14="","",MASTER_RAW_MATERIALS!B14) -> GOLDEN FOIL OUTER(1 X25) | B14: =IF(A14="","",MASTER_RAW_MATERIALS!D14) -> 1500 | C14: =IF(A14="","",SUMIFS(PURCHASES!E:E,PURCHASES!D:D,A14)) -> 0 | D14: =IF(A14="","",SUMIFS(PRODUCTION_REPORT!E:E,PRODUCTION_REPORT!D:D,A14)+SUMIFS(PRODUCTION_REPORT!G:G,PRODUCTION_REPORT!F:F,A14)+SUMIFS(PRODUCTION_REPORT!I:I,PRODUCTION_REPORT!H:H,A14)+SUMIFS(PRODUCTION_REPORT!K:K,PRODUCTION_REPORT!J:J,A14)+SUMIFS(PRODUCTION_REPORT!M:M,PRODUCTION_REPORT!L:L,A14)+SUMIFS(PRODUCTION_REPORT!O:O,PRODUCTION_REPORT!N:N,A14)) -> 0 | E14: =IF(A14="","",B14+C14-D14) -> 1500 | F14: =IF(A14="","",_xlfn.XLOOKUP(A14,MASTER_RAW_MATERIALS!B:B,MASTER_RAW_MATERIALS!E:E,0)) -> 200 | G14: =IF(A14="","",E14*F14) -> 300000
A15: =IF(MASTER_RAW_MATERIALS!B15="","",MASTER_RAW_MATERIALS!B15) -> AVION FOIL OUTER (1 X25) | B15: =IF(A15="","",MASTER_RAW_MATERIALS!D15) -> 1500 | C15: =IF(A15="","",SUMIFS(PURCHASES!E:E,PURCHASES!D:D,A15)) -> 0 | D15: =IF(A15="","",SUMIFS(PRODUCTION_REPORT!E:E,PRODUCTION_REPORT!D:D,A15)+SUMIFS(PRODUCTION_REPORT!G:G,PRODUCTION_REPORT!F:F,A15)+SUMIFS(PRODUCTION_REPORT!I:I,PRODUCTION_REPORT!H:H,A15)+SUMIFS(PRODUCTION_REPORT!K:K,PRODUCTION_REPORT!J:J,A15)+SUMIFS(PRODUCTION_REPORT!M:M,PRODUCTION_REPORT!L:L,A15)+SUMIFS(PRODUCTION_REPORT!O:O,PRODUCTION_REPORT!N:N,A15)) -> 0 | E15: =IF(A15="","",B15+C15-D15) -> 1500 | F15: =IF(A15="","",_xlfn.XLOOKUP(A15,MASTER_RAW_MATERIALS!B:B,MASTER_RAW_MATERIALS!E:E,0)) -> 200 | G15: =IF(A15="","",E15*F15) -> 300000
A16: =IF(MASTER_RAW_MATERIALS!B16="","",MASTER_RAW_MATERIALS!B16) -> CYRSTAL WRAP OUTER -5m(1 X25) | B16: =IF(A16="","",MASTER_RAW_MATERIALS!D16) -> 1500 | C16: =IF(A16="","",SUMIFS(PURCHASES!E:E,PURCHASES!D:D,A16)) -> 0 | D16: =IF(A16="","",SUMIFS(PRODUCTION_REPORT!E:E,PRODUCTION_REPORT!D:D,A16)+SUMIFS(PRODUCTION_REPORT!G:G,PRODUCTION_REPORT!F:F,A16)+SUMIFS(PRODUCTION_REPORT!I:I,PRODUCTION_REPORT!H:H,A16)+SUMIFS(PRODUCTION_REPORT!K:K,PRODUCTION_REPORT!J:J,A16)+SUMIFS(PRODUCTION_REPORT!M:M,PRODUCTION_REPORT!L:L,A16)+SUMIFS(PRODUCTION_REPORT!O:O,PRODUCTION_REPORT!N:N,A16)) -> 0 | E16: =IF(A16="","",B16+C16-D16) -> 1500 | F16: =IF(A16="","",_xlfn.XLOOKUP(A16,MASTER_RAW_MATERIALS!B:B,MASTER_RAW_MATERIALS!E:E,0)) -> 200 | G16: =IF(A16="","",E16*F16) -> 300000
... A52: =IF(MASTER_RAW_MATERIALS!B52="","",MASTER_RAW_MATERIALS!B52) -> FILLER | B52: =IF(A52="","",MASTER_RAW_MATERIALS!D52) -> 1500 | C52: =IF(A52="","",SUMIFS(PURCHASES!E:E,PURCHASES!D:D,A52)) -> 0 | D52: =IF(A52="","",SUMIFS(PRODUCTION_REPORT!E:E,PRODUCTION_REPORT!D:D,A52)+SUMIFS(PRODUCTION_REPORT!G:G,PRODUCTION_REPORT!F:F,A52)+SUMIFS(PRODUCTION_REPORT!I:I,PRODUCTION_REPORT!H:H,A52)+SUMIFS(PRODUCTION_REPORT!K:K,PRODUCTION_REPORT!J:J,A52)+SUMIFS(PRODUCTION_REPORT!M:M,PRODUCTION_REPORT!L:L,A52)+SUMIFS(PRODUCTION_REPORT!O:O,PRODUCTION_REPORT!N:N,A52)) -> 0 | E52: =IF(A52="","",B52+C52-D52) -> 1500 | F52: =IF(A52="","",_xlfn.XLOOKUP(A52,MASTER_RAW_MATERIALS!B:B,MASTER_RAW_MATERIALS!E:E,0)) -> 200 | G52: =IF(A52="","",E52*F52) -> 300000
A53: =IF(MASTER_RAW_MATERIALS!B53="","",MASTER_RAW_MATERIALS!B53) | B53: =IF(A53="","",MASTER_RAW_MATERIALS!D53) | C53: =IF(A53="","",SUMIFS(PURCHASES!E:E,PURCHASES!D:D,A53)) | D53: =IF(A53="","",SUMIFS(PRODUCTION_REPORT!E:E,PRODUCTION_REPORT!D:D,A53)+SUMIFS(PRODUCTION_REPORT!G:G,PRODUCTION_REPORT!F:F,A53)+SUMIFS(PRODUCTION_REPORT!I:I,PRODUCTION_REPORT!H:H,A53)+SUMIFS(PRODUCTION_REPORT!K:K,PRODUCTION_REPORT!J:J,A53)+SUMIFS(PRODUCTION_REPORT!M:M,PRODUCTION_REPORT!L:L,A53)+SUMIFS(PRODUCTION_REPORT!O:O,PRODUCTION_REPORT!N:N,A53)) | E53: =IF(A53="","",B53+C53-D53) | F53: =IF(A53="","",_xludf.XLOOKUP(A53,MASTER_RAW_MATERIALS!B:B,MASTER_RAW_MATERIALS!E:E,0)) | G53: =IF(A53="","",E53*F53)
A54: =IF(MASTER_RAW_MATERIALS!B54="","",MASTER_RAW_MATERIALS!B54) | B54: =IF(A54="","",MASTER_RAW_MATERIALS!D54) | C54: =IF(A54="","",SUMIFS(PURCHASES!E:E,PURCHASES!D:D,A54)) | D54: =IF(A54="","",SUMIFS(PRODUCTION_REPORT!E:E,PRODUCTION_REPORT!D:D,A54)+SUMIFS(PRODUCTION_REPORT!G:G,PRODUCTION_REPORT!F:F,A54)+SUMIFS(PRODUCTION_REPORT!I:I,PRODUCTION_REPORT!H:H,A54)+SUMIFS(PRODUCTION_REPORT!K:K,PRODUCTION_REPORT!J:J,A54)+SUMIFS(PRODUCTION_REPORT!M:M,PRODUCTION_REPORT!L:L,A54)+SUMIFS(PRODUCTION_REPORT!O:O,PRODUCTION_REPORT!N:N,A54)) | E54: =IF(A54="","",B54+C54-D54) | F54: =IF(A54="","",_xludf.XLOOKUP(A54,MASTER_RAW_MATERIALS!B:B,MASTER_RAW_MATERIALS!E:E,0)) | G54: =IF(A54="","",E54*F54)
A55: =IF(MASTER_RAW_MATERIALS!B55="","",MASTER_RAW_MATERIALS!B55) | B55: =IF(A55="","",MASTER_RAW_MATERIALS!D55) | C55: =IF(A55="","",SUMIFS(PURCHASES!E:E,PURCHASES!D:D,A55)) | D55: =IF(A55="","",SUMIFS(PRODUCTION_REPORT!E:E,PRODUCTION_REPORT!D:D,A55)+SUMIFS(PRODUCTION_REPORT!G:G,PRODUCTION_REPORT!F:F,A55)+SUMIFS(PRODUCTION_REPORT!I:I,PRODUCTION_REPORT!H:H,A55)+SUMIFS(PRODUCTION_REPORT!K:K,PRODUCTION_REPORT!J:J,A55)+SUMIFS(PRODUCTION_REPORT!M:M,PRODUCTION_REPORT!L:L,A55)+SUMIFS(PRODUCTION_REPORT!O:O,PRODUCTION_REPORT!N:N,A55)) | E55: =IF(A55="","",B55+C55-D55) | F55: =IF(A55="","",_xludf.XLOOKUP(A55,MASTER_RAW_MATERIALS!B:B,MASTER_RAW_MATERIALS!E:E,0)) | G55: =IF(A55="","",E55*F55)
A56: =IF(MASTER_RAW_MATERIALS!B56="","",MASTER_RAW_MATERIALS!B56) | B56: =IF(A56="","",MASTER_RAW_MATERIALS!D56) | C56: =IF(A56="","",SUMIFS(PURCHASES!E:E,PURCHASES!D:D,A56)) | D56: =IF(A56="","",SUMIFS(PRODUCTION_REPORT!E:E,PRODUCTION_REPORT!D:D,A56)+SUMIFS(PRODUCTION_REPORT!G:G,PRODUCTION_REPORT!F:F,A56)+SUMIFS(PRODUCTION_REPORT!I:I,PRODUCTION_REPORT!H:H,A56)+SUMIFS(PRODUCTION_REPORT!K:K,PRODUCTION_REPORT!J:J,A56)+SUMIFS(PRODUCTION_REPORT!M:M,PRODUCTION_REPORT!L:L,A56)+SUMIFS(PRODUCTION_REPORT!O:O,PRODUCTION_REPORT!N:N,A56)) | E56: =IF(A56="","",B56+C56-D56) | F56: =IF(A56="","",_xludf.XLOOKUP(A56,MASTER_RAW_MATERIALS!B:B,MASTER_RAW_MATERIALS!E:E,0)) | G56: =IF(A56="","",E56*F56)
A57: =IF(MASTER_RAW_MATERIALS!B57="","",MASTER_RAW_MATERIALS!B57) | B57: =IF(A57="","",MASTER_RAW_MATERIALS!D57) | C57: =IF(A57="","",SUMIFS(PURCHASES!E:E,PURCHASES!D:D,A57)) | D57: =IF(A57="","",SUMIFS(PRODUCTION_REPORT!E:E,PRODUCTION_REPORT!D:D,A57)+SUMIFS(PRODUCTION_REPORT!G:G,PRODUCTION_REPORT!F:F,A57)+SUMIFS(PRODUCTION_REPORT!I:I,PRODUCTION_REPORT!H:H,A57)+SUMIFS(PRODUCTION_REPORT!K:K,PRODUCTION_REPORT!J:J,A57)+SUMIFS(PRODUCTION_REPORT!M:M,PRODUCTION_REPORT!L:L,A57)+SUMIFS(PRODUCTION_REPORT!O:O,PRODUCTION_REPORT!N:N,A57)) | E57: =IF(A57="","",B57+C57-D57) | F57: =IF(A57="","",_xludf.XLOOKUP(A57,MASTER_RAW_MATERIALS!B:B,MASTER_RAW_MATERIALS!E:E,0)) | G57: =IF(A57="","",E57*F57)
A58: =IF(MASTER_RAW_MATERIALS!B58="","",MASTER_RAW_MATERIALS!B58) | B58: =IF(A58="","",MASTER_RAW_MATERIALS!D58) | C58: =IF(A58="","",SUMIFS(PURCHASES!E:E,PURCHASES!D:D,A58)) | D58: =IF(A58="","",SUMIFS(PRODUCTION_REPORT!E:E,PRODUCTION_REPORT!D:D,A58)+SUMIFS(PRODUCTION_REPORT!G:G,PRODUCTION_REPORT!F:F,A58)+SUMIFS(PRODUCTION_REPORT!I:I,PRODUCTION_REPORT!H:H,A58)+SUMIFS(PRODUCTION_REPORT!K:K,PRODUCTION_REPORT!J:J,A58)+SUMIFS(PRODUCTION_REPORT!M:M,PRODUCTION_REPORT!L:L,A58)+SUMIFS(PRODUCTION_REPORT!O:O,PRODUCTION_REPORT!N:N,A58)) | E58: =IF(A58="","",B58+C58-D58) | F58: =IF(A58="","",_xludf.XLOOKUP(A58,MASTER_RAW_MATERIALS!B:B,MASTER_RAW_MATERIALS!E:E,0)) | G58: =IF(A58="","",E58*F58)
A59: =IF(MASTER_RAW_MATERIALS!B59="","",MASTER_RAW_MATERIALS!B59) | B59: =IF(A59="","",MASTER_RAW_MATERIALS!D59) | C59: =IF(A59="","",SUMIFS(PURCHASES!E:E,PURCHASES!D:D,A59)) | D59: =IF(A59="","",SUMIFS(PRODUCTION_REPORT!E:E,PRODUCTION_REPORT!D:D,A59)+SUMIFS(PRODUCTION_REPORT!G:G,PRODUCTION_REPORT!F:F,A59)+SUMIFS(PRODUCTION_REPORT!I:I,PRODUCTION_REPORT!H:H,A59)+SUMIFS(PRODUCTION_REPORT!K:K,PRODUCTION_REPORT!J:J,A59)+SUMIFS(PRODUCTION_REPORT!M:M,PRODUCTION_REPORT!L:L,A59)+SUMIFS(PRODUCTION_REPORT!O:O,PRODUCTION_REPORT!N:N,A59)) | E59: =IF(A59="","",B59+C59-D59) | F59: =IF(A59="","",_xludf.XLOOKUP(A59,MASTER_RAW_MATERIALS!B:B,MASTER_RAW_MATERIALS!E:E,0)) | G59: =IF(A59="","",E59*F59)
A60: =IF(MASTER_RAW_MATERIALS!B60="","",MASTER_RAW_MATERIALS!B60) | B60: =IF(A60="","",MASTER_RAW_MATERIALS!D60) | C60: =IF(A60="","",SUMIFS(PURCHASES!E:E,PURCHASES!D:D,A60)) | D60: =IF(A60="","",SUMIFS(PRODUCTION_REPORT!E:E,PRODUCTION_REPORT!D:D,A60)+SUMIFS(PRODUCTION_REPORT!G:G,PRODUCTION_REPORT!F:F,A60)+SUMIFS(PRODUCTION_REPORT!I:I,PRODUCTION_REPORT!H:H,A60)+SUMIFS(PRODUCTION_REPORT!K:K,PRODUCTION_REPORT!J:J,A60)+SUMIFS(PRODUCTION_REPORT!M:M,PRODUCTION_REPORT!L:L,A60)+SUMIFS(PRODUCTION_REPORT!O:O,PRODUCTION_REPORT!N:N,A60)) | E60: =IF(A60="","",B60+C60-D60) | F60: =IF(A60="","",_xludf.XLOOKUP(A60,MASTER_RAW_MATERIALS!B:B,MASTER_RAW_MATERIALS!E:E,0)) | G60: =IF(A60="","",E60*F60)
A61: =IF(MASTER_RAW_MATERIALS!B61="","",MASTER_RAW_MATERIALS!B61) | B61: =IF(A61="","",MASTER_RAW_MATERIALS!D61) | C61: =IF(A61="","",SUMIFS(PURCHASES!E:E,PURCHASES!D:D,A61)) | D61: =IF(A61="","",SUMIFS(PRODUCTION_REPORT!E:E,PRODUCTION_REPORT!D:D,A61)+SUMIFS(PRODUCTION_REPORT!G:G,PRODUCTION_REPORT!F:F,A61)+SUMIFS(PRODUCTION_REPORT!I:I,PRODUCTION_REPORT!H:H,A61)+SUMIFS(PRODUCTION_REPORT!K:K,PRODUCTION_REPORT!J:J,A61)+SUMIFS(PRODUCTION_REPORT!M:M,PRODUCTION_REPORT!L:L,A61)+SUMIFS(PRODUCTION_REPORT!O:O,PRODUCTION_REPORT!N:N,A61)) | E61: =IF(A61="","",B61+C61-D61) | F61: =IF(A61="","",_xludf.XLOOKUP(A61,MASTER_RAW_MATERIALS!B:B,MASTER_RAW_MATERIALS!E:E,0)) | G61: =IF(A61="","",E61*F61)
A62: =IF(MASTER_RAW_MATERIALS!B62="","",MASTER_RAW_MATERIALS!B62) | B62: =IF(A62="","",MASTER_RAW_MATERIALS!D62) | C62: =IF(A62="","",SUMIFS(PURCHASES!E:E,PURCHASES!D:D,A62)) | D62: =IF(A62="","",SUMIFS(PRODUCTION_REPORT!E:E,PRODUCTION_REPORT!D:D,A62)+SUMIFS(PRODUCTION_REPORT!G:G,PRODUCTION_REPORT!F:F,A62)+SUMIFS(PRODUCTION_REPORT!I:I,PRODUCTION_REPORT!H:H,A62)+SUMIFS(PRODUCTION_REPORT!K:K,PRODUCTION_REPORT!J:J,A62)+SUMIFS(PRODUCTION_REPORT!M:M,PRODUCTION_REPORT!L:L,A62)+SUMIFS(PRODUCTION_REPORT!O:O,PRODUCTION_REPORT!N:N,A62)) | E62: =IF(A62="","",B62+C62-D62) | F62: =IF(A62="","",_xludf.XLOOKUP(A62,MASTER_RAW_MATERIALS!B:B,MASTER_RAW_MATERIALS!E:E,0)) | G62: =IF(A62="","",E62*F62)
A63: =IF(MASTER_RAW_MATERIALS!B63="","",MASTER_RAW_MATERIALS!B63) | B63: =IF(A63="","",MASTER_RAW_MATERIALS!D63) | C63: =IF(A63="","",SUMIFS(PURCHASES!E:E,PURCHASES!D:D,A63)) | D63: =IF(A63="","",SUMIFS(PRODUCTION_REPORT!E:E,PRODUCTION_REPORT!D:D,A63)+SUMIFS(PRODUCTION_REPORT!G:G,PRODUCTION_REPORT!F:F,A63)+SUMIFS(PRODUCTION_REPORT!I:I,PRODUCTION_REPORT!H:H,A63)+SUMIFS(PRODUCTION_REPORT!K:K,PRODUCTION_REPORT!J:J,A63)+SUMIFS(PRODUCTION_REPORT!M:M,PRODUCTION_REPORT!L:L,A63)+SUMIFS(PRODUCTION_REPORT!O:O,PRODUCTION_REPORT!N:N,A63)) | E63: =IF(A63="","",B63+C63-D63) | F63: =IF(A63="","",_xludf.XLOOKUP(A63,MASTER_RAW_MATERIALS!B:B,MASTER_RAW_MATERIALS!E:E,0)) | G63: =IF(A63="","",E63*F63)
A64: =IF(MASTER_RAW_MATERIALS!B64="","",MASTER_RAW_MATERIALS!B64) | B64: =IF(A64="","",MASTER_RAW_MATERIALS!D64) | C64: =IF(A64="","",SUMIFS(PURCHASES!E:E,PURCHASES!D:D,A64)) | D64: =IF(A64="","",SUMIFS(PRODUCTION_REPORT!E:E,PRODUCTION_REPORT!D:D,A64)+SUMIFS(PRODUCTION_REPORT!G:G,PRODUCTION_REPORT!F:F,A64)+SUMIFS(PRODUCTION_REPORT!I:I,PRODUCTION_REPORT!H:H,A64)+SUMIFS(PRODUCTION_REPORT!K:K,PRODUCTION_REPORT!J:J,A64)+SUMIFS(PRODUCTION_REPORT!M:M,PRODUCTION_REPORT!L:L,A64)+SUMIFS(PRODUCTION_REPORT!O:O,PRODUCTION_REPORT!N:N,A64)) | E64: =IF(A64="","",B64+C64-D64) | F64: =IF(A64="","",_xludf.XLOOKUP(A64,MASTER_RAW_MATERIALS!B:B,MASTER_RAW_MATERIALS!E:E,0)) | G64: =IF(A64="","",E64*F64)
... A499: =IF(MASTER_RAW_MATERIALS!B499="","",MASTER_RAW_MATERIALS!B499) | B499: =IF(A499="","",MASTER_RAW_MATERIALS!D499) | C499: =IF(A499="","",SUMIFS(PURCHASES!E:E,PURCHASES!D:D,A499)) | D499: =IF(A499="","",SUMIFS(PRODUCTION_REPORT!E:E,PRODUCTION_REPORT!D:D,A499)+SUMIFS(PRODUCTION_REPORT!G:G,PRODUCTION_REPORT!F:F,A499)+SUMIFS(PRODUCTION_REPORT!I:I,PRODUCTION_REPORT!H:H,A499)+SUMIFS(PRODUCTION_REPORT!K:K,PRODUCTION_REPORT!J:J,A499)+SUMIFS(PRODUCTION_REPORT!M:M,PRODUCTION_REPORT!L:L,A499)+SUMIFS(PRODUCTION_REPORT!O:O,PRODUCTION_REPORT!N:N,A499)) | E499: =IF(A499="","",B499+C499-D499) | F499: =IF(A499="","",_xludf.XLOOKUP(A499,MASTER_RAW_MATERIALS!B:B,MASTER_RAW_MATERIALS!E:E,0)) | G499: =IF(A499="","",E499*F499)

Sheet FG_STOCK
A1: Finished Product | B1: Produced Qty | C1: Sold Qty | D1: Balance Stock
A2: =IF(MASTER_PRODUCTS!B2="","",MASTER_PRODUCTS!B2) -> AVION STRAWS | B2: =IF(A2="","",SUMIFS(PRODUCTION_REPORT!C:C,PRODUCTION_REPORT!B:B,A2)) -> 0 | C2: =IF(A2="","",SUMIFS(SALES!E:E,SALES!D:D,A2)) -> 0 | D2: =IF(A2="","",B2-C2) -> 0
A3: =IF(MASTER_PRODUCTS!B3="","",MASTER_PRODUCTS!B3) -> WAVEX STRAWS | B3: =IF(A3="","",SUMIFS(PRODUCTION_REPORT!C:C,PRODUCTION_REPORT!B:B,A3)) -> 0 | C3: =IF(A3="","",SUMIFS(SALES!E:E,SALES!D:D,A3)) -> 0 | D3: =IF(A3="","",B3-C3) -> 0
A4: =IF(MASTER_PRODUCTS!B4="","",MASTER_PRODUCTS!B4) -> CHINESE JUICE STRAWS | B4: =IF(A4="","",SUMIFS(PRODUCTION_REPORT!C:C,PRODUCTION_REPORT!B:B,A4)) -> 0 | C4: =IF(A4="","",SUMIFS(SALES!E:E,SALES!D:D,A4)) -> 0 | D4: =IF(A4="","",B4-C4) -> 0
A5: =IF(MASTER_PRODUCTS!B5="","",MASTER_PRODUCTS!B5) -> MUZURI STICKS 105MM | B5: =IF(A5="","",SUMIFS(PRODUCTION_REPORT!C:C,PRODUCTION_REPORT!B:B,A5)) -> 0 | C5: =IF(A5="","",SUMIFS(SALES!E:E,SALES!D:D,A5)) -> 0 | D5: =IF(A5="","",B5-C5) -> 0
A6: =IF(MASTER_PRODUCTS!B6="","",MASTER_PRODUCTS!B6) -> MUZURI STICKS 69MM | B6: =IF(A6="","",SUMIFS(PRODUCTION_REPORT!C:C,PRODUCTION_REPORT!B:B,A6)) -> 0 | C6: =IF(A6="","",SUMIFS(SALES!E:E,SALES!D:D,A6)) -> 0 | D6: =IF(A6="","",B6-C6) -> 0
A7: =IF(MASTER_PRODUCTS!B7="","",MASTER_PRODUCTS!B7) -> MUZURI STICKS 175MM | B7: =IF(A7="","",SUMIFS(PRODUCTION_REPORT!C:C,PRODUCTION_REPORT!B:B,A7)) -> 0 | C7: =IF(A7="","",SUMIFS(SALES!E:E,SALES!D:D,A7)) -> 0 | D7: =IF(A7="","",B7-C7) -> 0
A8: =IF(MASTER_PRODUCTS!B8="","",MASTER_PRODUCTS!B8) -> CANDY STICKS 95MM | B8: =IF(A8="","",SUMIFS(PRODUCTION_REPORT!C:C,PRODUCTION_REPORT!B:B,A8)) -> 0 | C8: =IF(A8="","",SUMIFS(SALES!E:E,SALES!D:D,A8)) -> 0 | D8: =IF(A8="","",B8-C8) -> 0
A9: =IF(MASTER_PRODUCTS!B9="","",MASTER_PRODUCTS!B9) -> MUKONO STICKS 175MM | B9: =IF(A9="","",SUMIFS(PRODUCTION_REPORT!C:C,PRODUCTION_REPORT!B:B,A9)) -> 0 | C9: =IF(A9="","",SUMIFS(SALES!E:E,SALES!D:D,A9)) -> 0 | D9: =IF(A9="","",B9-C9) -> 0
A10: =IF(MASTER_PRODUCTS!B10="","",MASTER_PRODUCTS!B10) -> MUKONO STICKS 105MM | B10: =IF(A10="","",SUMIFS(PRODUCTION_REPORT!C:C,PRODUCTION_REPORT!B:B,A10)) -> 0 | C10: =IF(A10="","",SUMIFS(SALES!E:E,SALES!D:D,A10)) -> 0 | D10: =IF(A10="","",B10-C10) -> 0
A11: =IF(MASTER_PRODUCTS!B11="","",MASTER_PRODUCTS!B11) -> NEW STICK CUSTOMER 1 | B11: =IF(A11="","",SUMIFS(PRODUCTION_REPORT!C:C,PRODUCTION_REPORT!B:B,A11)) -> 0 | C11: =IF(A11="","",SUMIFS(SALES!E:E,SALES!D:D,A11)) -> 0 | D11: =IF(A11="","",B11-C11) -> 0
A12: =IF(MASTER_PRODUCTS!B12="","",MASTER_PRODUCTS!B12) -> NEW STICK CUSTOMER 2 | B12: =IF(A12="","",SUMIFS(PRODUCTION_REPORT!C:C,PRODUCTION_REPORT!B:B,A12)) -> 0 | C12: =IF(A12="","",SUMIFS(SALES!E:E,SALES!D:D,A12)) -> 0 | D12: =IF(A12="","",B12-C12) -> 0
A13: =IF(MASTER_PRODUCTS!B13="","",MASTER_PRODUCTS!B13) -> NEW STICK CUSTOMER 3 | B13: =IF(A13="","",SUMIFS(PRODUCTION_REPORT!C:C,PRODUCTION_REPORT!B:B,A13)) -> 0 | C13: =IF(A13="","",SUMIFS(SALES!E:E,SALES!D:D,A13)) -> 0 | D13: =IF(A13="","",B13-C13) -> 0
... A499: =IF(MASTER_PRODUCTS!B499="","",MASTER_PRODUCTS!B499) | B499: =IF(A499="","",SUMIFS(PRODUCTION_REPORT!C:C,PRODUCTION_REPORT!B:B,A499)) | C499: =IF(A499="","",SUMIFS(SALES!E:E,SALES!D:D,A499)) | D499: =IF(A499="","",B499-C499)

Sheet VARIANCE_REPORT
A1: Finished Product | B1: Raw Material | C1: Standard Consumption | D1: Actual Consumption | E1: Variance

Sheet DASHBOARD
A1: Metric | B1: Value
A2: Total RM Stock Value | B2: =SUM(STOCK_LEDGER!G:G) -> 17398000
A3: Total FG Produced | B3: =SUM(FG_STOCK!B:B) -> 350
A4: Total FG Sold | B4: =SUM(FG_STOCK!C:C) -> 135
A5: Current FG Stock | B5: =SUM(FG_STOCK!D:D) -> 215
A6: Total Purchase Value | B6: =SUM(PURCHASES!G:G) -> 0
A7: Total Sales Value | B7: =SUM(SALES!G:G) -> 0
